spark/__about__.py
spark/__init__.py
spark/messages.py
spark/people.py
spark/rooms.py
spark/session.py
spark/teams.py
spark/webhooks.py
spark_python-0.0.13.dist-info/DESCRIPTION.rst
spark_python-0.0.13.dist-info/METADATA
spark_python-0.0.13.dist-info/RECORD
spark_python-0.0.13.dist-info/WHEEL
spark_python-0.0.13.dist-info/metadata.json
spark_python-0.0.13.dist-info/top_level.txt
