Metadata-Version: 2.0
Name: spark-python
Version: 0.0.13
Summary: Python bindings for Cisco Spark API
Home-page: http://github.com/imapex/spark-python
Author: Cisco Systems, Inc.
Author-email: imapex-admin@cisco.com
License: Apache License, Version 2.0
Platform: UNKNOWN
Requires-Dist: requests
